{"cameraMode":{"drawMode":0,"name":"Shaded","section":"Shading Mode"},"sceneLighting":true,"audioPlay":false,"sceneViewState":{"showFog":true,"showMaterialUpdate":false,"showSkybox":true,"showFlares":true,"showImageEffects":true,"showParticleSystems":true},"in2DMode":false,"pivot":{"x":536.9851684570313,"y":529.5582275390625,"z":-419.676513671875},"rotation":{"x":-0.16494274139404298,"y":0.1133129820227623,"z":-0.019134866073727609,"w":-0.9796748161315918},"size":202.425048828125,"orthographic":false}